netifaces.cp38-win32.pyd
netifaces-0.11.0.dist-info/LICENSE
netifaces-0.11.0.dist-info/METADATA
netifaces-0.11.0.dist-info/WHEEL
netifaces-0.11.0.dist-info/top_level.txt
netifaces-0.11.0.dist-info/zip-safe
netifaces-0.11.0.dist-info/RECORD
